dockerz/__init__.py
dockerz/__main__.py
dockerz/builder.py
dockerz/cli.py
dockerz-1.0.4.dist-info/METADATA
dockerz-1.0.4.dist-info/WHEEL
dockerz-1.0.4.dist-info/entry_points.txt
dockerz-1.0.4.dist-info/RECORD
