Metadata-Version: 2.4
Name: dockerz
Version: 1.0.4
Summary: A CLI tool to build and push multiple Docker images in parallel.
Requires-Python: >=3.8
Requires-Dist: click>=8.1.0
Requires-Dist: pyyaml>=6.0
